memoria.v
module memoria #(
    parameter MEM_WORDS = 1024
)(
    input  wire        clock,
    input  wire        mem_enable,
    input  wire        mem_op,      // 0=read, 1=write
    input  wire [31:0] MAR,         // endereço por PALAVRA
    input  wire [31:0] MBR_out,     // dado para escrita
    output reg  [31:0] MBR_in       // dado lido (válido 1 ciclo após read)
);
    reg [31:0] mem [0:MEM_WORDS-1];

    // Escrita síncrona
    always @(posedge clock) begin
        if (mem_enable && mem_op) begin
            mem[MAR] <= MBR_out;
        end
    end

    // Leitura com latência de 1 ciclo
    always @(posedge clock) begin
        if (mem_enable && !mem_op) begin
            MBR_in <= mem[MAR];
        end
    end
endmodule

ula.v
module ula(
    input  wire [2:0]  op,   // 0:add 1:sub 2:and 3:or 4:not 5:mul 6:div
    input  wire [31:0] a,
    input  wire [31:0] b,
    output reg  [31:0] y,
    output wire        Z,
    output wire        N
);
    always @* begin
        case (op)
            3'd0:  y = a + b;                     // ADD
            3'd1:  y = a - b;                     // SUB
            3'd2:  y = a & b;                     // AND
            3'd3:  y = a | b;                     // OR
            3'd4:  y = ~a;                        // NOT (unário)
            3'd5:  y = a * b;                     // MUL (trunc 32b)
            3'd6:  y = (b==0) ? 32'd0 : (a / b);  // DIV (div/0 -> 0)
            default:y = 32'd0;
        endcase
    end

    assign Z = (y == 32'd0);
    assign N = y[31];
endmodule

banco_registradores.v
module banco_registradores(
    input  wire        clock,
    input  wire        we,
    input  wire [4:0]  waddr,
    input  wire [31:0] wdata,
    input  wire [4:0]  rs,
    input  wire [4:0]  rt,
    output wire [31:0] rs_data,
    output wire [31:0] rt_data
);
    reg [31:0] regs [0:31];

    assign rs_data = regs[rs];
    assign rt_data = regs[rt];

    always @(posedge clock) begin
        if (we) regs[waddr] <= wdata;
    end

    integer i;
    initial begin
        for (i=0; i<32; i=i+1) regs[i] = 32'd0;
    end
endmodule

processador.v
// processador.v
// CPU 32-bit – FSM multiciclo – interface MAR/MBR_in/MBR_out/mem_enable/mem_op

module processador(
    input  wire        clock,
    input  wire        reset,         // reset síncrono
    // Interface de memória unificada (endereçada por PALAVRA)
    output reg  [31:0] MAR,
    input  wire [31:0] MBR_in,
    output reg  [31:0] MBR_out,
    output reg         mem_enable,    // 1 = acesso ativo
    output reg         mem_op,        // 0 = leitura, 1 = escrita
    // E/S mapeada
    input  wire [31:0] input_data,
    output reg  [31:0] output_data
);

    // -------- opcodes/funct --------
    localparam OP_RTYPE   = 6'h00;
    localparam OP_JMP     = 6'h02;

    localparam OP_JE      = 6'h04;
    localparam OP_JNE     = 6'h05;
    localparam OP_JG      = 6'h06;
    localparam OP_JGE     = 6'h07;

    localparam OP_LOADEXT = 6'h20;
    localparam OP_STOREEXT= 6'h2A;

    localparam OP_LOAD    = 6'h23;
    localparam OP_STORE   = 6'h2B;

    localparam OP_LCH     = 6'h0F;
    localparam OP_LCL     = 6'h0D;

    localparam OP_JL      = 6'h1E;
    localparam OP_JLE     = 6'h1F;

    localparam FUNCT_ADD  = 6'h20;
    localparam FUNCT_SUB  = 6'h22;
    localparam FUNCT_AND  = 6'h24;
    localparam FUNCT_OR   = 6'h25;
    localparam FUNCT_NOT  = 6'h2F; // unário (usa rs)
    localparam FUNCT_MUL  = 6'h18;
    localparam FUNCT_DIV  = 6'h1A;

    // -------- registradores/decod --------
    reg [31:0] PC, IR;
    wire [5:0]  opcode = IR[31:26];
    wire [4:0]  rs     = IR[25:21];
    wire [4:0]  rt     = IR[20:16];
    wire [4:0]  rd     = IR[15:11];
    wire [5:0]  funct  = IR[5:0];
    wire [15:0] imm16  = IR[15:0];
    wire [25:0] off26  = IR[25:0];

    wire signed [31:0] IMM_SEXT  = {{16{imm16[15]}}, imm16};    // p/ Load/Store/Branch (offset em PALAVRAS)
    wire        [31:0] IMM_ZEXT  = {16'b0, imm16};              // p/ LCL
    wire signed [31:0] OFF26_SEX = {{6{off26[25]}}, off26};     // JMP (26b) em PALAVRAS

    // Banco de registradores (32x32)
    wire [31:0] rs_data, rt_data;
    reg         rf_we;
    reg  [4:0]  rf_waddr;
    reg  [31:0] rf_wdata;

    banco_registradores rf (
        .clock (clock), .we (rf_we),
        .waddr (rf_waddr), .wdata (rf_wdata),
        .rs (rs), .rt (rt),
        .rs_data (rs_data), .rt_data (rt_data)
    );

    // ULA
    localparam ALU_ADD=3'd0, ALU_SUB=3'd1, ALU_AND=3'd2, ALU_OR=3'd3,
               ALU_NOT=3'd4, ALU_MUL=3'd5, ALU_DIV=3'd6;

    reg  [2:0]  alu_op;
    reg  [31:0] alu_a, alu_b;
    wire [31:0] alu_y;
    wire        alu_z, alu_n;

    ula ULA (.op(alu_op), .a(alu_a), .b(alu_b), .y(alu_y), .Z(alu_z), .N(alu_n));

    // Flags e endereço efetivo
    reg flagZ, flagN;
    reg [31:0] eff_addr;
    reg take_branch;

    // “next” para saída de E/S (robusto)
    reg [31:0] output_data_next;

    // -------- FSM --------
    localparam S_RESET=4'd0, S_FETCH=4'd1, S_FETCH_WAIT=4'd2, S_DECODE=4'd3,
               S_EXEC_R=4'd4, S_LCH=4'd5, S_LCL=4'd6, S_MEM_ADDR=4'd7,
               S_MEM_READ=4'd8, S_MEM_READ_WAIT=4'd9, S_MEM_WRITE=4'd10,
               S_MEM_WRITE_WAIT=4'd11, S_BRANCH=4'd12, S_JUMP=4'd13,
               S_LOADEXT=4'd14, S_STOREEXT=4'd15;

    reg [3:0] state, next_state;

    // Estado
    always @(posedge clock) begin
        if (reset) begin
            state <= S_RESET; PC <= 32'd0; IR <= 32'd0;
            flagZ <= 1'b0; flagN <= 1'b0;
            mem_enable <= 1'b0; mem_op <= 1'b0;
            MAR <= 32'd0; MBR_out <= 32'd0;
            rf_we <= 1'b0;
            output_data <= 32'd0; output_data_next <= 32'd0;
        end else begin
            state <= next_state;
            output_data <= output_data_next; // aplica “next” a cada ciclo
        end
    end

    // Controle combinacional
    always @* begin
        next_state = state;

        // defaults seguros
        rf_we = 1'b0; rf_waddr = 5'd0; rf_wdata = 32'd0;
        mem_enable = 1'b0; mem_op = 1'b0; MAR = 32'd0; MBR_out = 32'd0;
        alu_op = ALU_ADD; alu_a = rs_data; alu_b = rt_data;
        output_data_next = output_data;

        case (state)
            S_RESET: next_state = S_FETCH;

            // Busca (latência 1 ciclo)
            S_FETCH: begin
                mem_enable = 1'b1; mem_op = 1'b0; MAR = PC;
                next_state = S_FETCH_WAIT;
            end

            S_FETCH_WAIT: next_state = S_DECODE;

            S_DECODE: begin
                case (opcode)
                    OP_RTYPE:   next_state = S_EXEC_R;
                    OP_LCH:     next_state = S_LCH;
                    OP_LCL:     next_state = S_LCL;
                    OP_LOAD,
                    OP_STORE:   next_state = S_MEM_ADDR;
                    OP_LOADEXT: next_state = S_LOADEXT;
                    OP_STOREEXT:next_state = S_STOREEXT;
                    OP_JE, OP_JNE, OP_JG, OP_JGE, OP_JL, OP_JLE: next_state = S_BRANCH;
                    OP_JMP:     next_state = S_JUMP;
                    default:    next_state = S_FETCH; // NOP
                endcase
            end

            // Tipo-R
            S_EXEC_R: begin
                case (funct)
                    FUNCT_ADD: alu_op = ALU_ADD;
                    FUNCT_SUB: alu_op = ALU_SUB;
                    FUNCT_AND: alu_op = ALU_AND;
                    FUNCT_OR : alu_op = ALU_OR;
                    FUNCT_NOT: begin alu_op = ALU_NOT; alu_a = rs_data; alu_b = 32'd0; end
                    FUNCT_MUL: alu_op = ALU_MUL;
                    FUNCT_DIV: alu_op = ALU_DIV;
                    default:    alu_op = ALU_ADD;
                endcase
                rf_we = 1'b1; rf_waddr = rd; rf_wdata = alu_y;
                next_state = S_FETCH;
            end

            // LCH/LCL (usam rt_data — sem acesso hierárquico)
            S_LCH: begin
                rf_we = 1'b1; rf_waddr = rt; rf_wdata = {imm16, rt_data[15:0]};
                next_state = S_FETCH;
            end

            S_LCL: begin
                rf_we = 1'b1; rf_waddr = rt; rf_wdata = {rt_data[31:16], imm16};
                next_state = S_FETCH;
            end

            // Endereço efetivo para Load/Store: R[rs] + imm (sign-extend)
            S_MEM_ADDR: begin
                alu_op = ALU_ADD; alu_a = rs_data; alu_b = IMM_SEXT;
                next_state = (opcode == OP_LOAD) ? S_MEM_READ : S_MEM_WRITE;
            end

            // Leitura
            S_MEM_READ: begin
                mem_enable = 1'b1; mem_op = 1'b0; MAR = eff_addr;
                next_state = S_MEM_READ_WAIT;
            end

            S_MEM_READ_WAIT: begin
                rf_we = 1'b1; rf_waddr = rt; rf_wdata = MBR_in;
                next_state = S_FETCH;
            end

            // Escrita
            S_MEM_WRITE: begin
                mem_enable = 1'b1; mem_op = 1'b1; MAR = eff_addr; MBR_out = rt_data;
                next_state = S_MEM_WRITE_WAIT;
            end
            S_MEM_WRITE_WAIT: next_state = S_FETCH;

            // Desvios / salto
            S_BRANCH: next_state = S_FETCH;
            S_JUMP:   next_state = S_FETCH;

            // E/S mapeada
            S_LOADEXT: begin
                rf_we = 1'b1; rf_waddr = rt; rf_wdata = input_data;
                next_state = S_FETCH;
            end
            S_STOREEXT: begin
                // Atualiza saída via registrador “next” (robusto)
                output_data_next = rt_data;
                next_state = S_FETCH;
            end

            default: next_state = S_FETCH;
        endcase
    end

    // Atualizações síncronas (IR, PC, flags, endereço efetivo)
    always @(posedge clock) begin
        if (!reset) begin
            case (state)
                S_FETCH_WAIT: IR <= MBR_in;

                S_EXEC_R:     begin flagZ <= alu_z; flagN <= alu_n; PC <= PC + 32'd1; end
                S_LCH,
                S_LCL,
                S_MEM_READ_WAIT,
                S_MEM_WRITE_WAIT,
                S_LOADEXT,
                S_STOREEXT:   PC <= PC + 32'd1;

                S_MEM_ADDR:   eff_addr <= alu_y;

                S_BRANCH: begin
                    take_branch = 1'b0;
                    case (opcode)
                        OP_JE:   take_branch = (flagZ == 1'b1);
                        OP_JNE:  take_branch = (flagZ == 1'b0);
                        OP_JG:   take_branch = (flagN == 1'b0) && (flagZ == 1'b0);
                        OP_JGE:  take_branch = (flagN == 1'b0);
                        OP_JL:   take_branch = (flagN == 1'b1);
                        OP_JLE:  take_branch = (flagN == 1'b1) || (flagZ == 1'b1);
                    endcase
                    PC <= take_branch ? (PC + IMM_SEXT) : (PC + 32'd1);
                end

                S_JUMP:       PC <= PC + OFF26_SEX;
            endcase
        end
    end
endmodule

tb_top.v
`timescale 1ns/1ps

module tb_top;
    reg  clock = 0;
    reg  reset = 1;

    // Barramento memória
    wire [31:0] MAR;
    wire [31:0] MBR_in;
    wire [31:0] MBR_out;
    wire        mem_enable;
    wire        mem_op;

    // E/S externa
    reg  [31:0] input_data;
    wire [31:0] output_data;

    // DUT
    processador dut (
        .clock(clock),
        .reset(reset),
        .MAR(MAR),
        .MBR_in(MBR_in),
        .MBR_out(MBR_out),
        .mem_enable(mem_enable),
        .mem_op(mem_op),
        .input_data(input_data),
        .output_data(output_data)
    );

    // Memória unificada
    memoria #(.MEM_WORDS(256)) ram (
        .clock(clock),
        .mem_enable(mem_enable),
        .mem_op(mem_op),
        .MAR(MAR),
        .MBR_out(MBR_out),
        .MBR_in(MBR_in)
    );

    // Clock 100MHz (10ns período)
    always #5 clock = ~clock;

    // Dumps
    initial begin
        $dumpfile("wave.vcd");
        $dumpvars(0, tb_top);
    end

    // Carrega programa na RAM (somente 0..18 -> sem WARNING)
    task load_program;
        integer i;
        begin
            for (i=0; i<256; i=i+1) ram.mem[i] = 32'h0000_0000;
            $readmemh("program.hex", ram.mem, 0, 18);
        end
    endtask

    // Reset síncrono
    task do_reset;
        begin
            reset = 1;
            repeat (3) @(posedge clock);
            reset = 0;
        end
    endtask

    // Espera laço final (PC preso em 18 por alguns ciclos)
    task wait_final;
        integer stuck;
        begin
            stuck = 0;
            repeat (300) begin
                @(posedge clock);
                if (dut.PC == 32'd18) stuck = stuck + 1;
                else                   stuck = 0;
                if (stuck >= 4) disable wait_final;
            end
        end
    endtask

    // Impressão requerida + asserts
    task print_and_check(input integer scenario);
        reg [31:0] R0,R1,R2,R3,R4,R5;
        begin
            R0 = dut.rf.regs[0];
            R1 = dut.rf.regs[1];
            R2 = dut.rf.regs[2];
            R3 = dut.rf.regs[3];
            R4 = dut.rf.regs[4];
            R5 = dut.rf.regs[5];

            $display("\n=== RESULTADOS (cenario=%0d) ===", scenario);
            $display("Reg0=%0d Reg1=%0d Reg2=%0d Reg3=%0d Reg4=%0d Reg5=%0d",
                      R0, R1, R2, R3, R4, R5);
            $display("Mem[1]=%0d  Mem[2]=%0d  output_data=%0d",
                      ram.mem[32'd1], ram.mem[32'd2], output_data);

            // Checks segundo o enunciado (duas simulações e impressões obrigatórias)
            // BCC720: imprimir Reg0..Reg5, output_data, Mem[1], Mem[2]; cenários 10 e 20. 
            if (scenario == 10) begin
                if (ram.mem[1] !== 32'd1)   $fatal(1, "Esperado Mem[1]=1 no cenario 10");
                if (ram.mem[2] !== 32'd16)  $fatal(1, "Esperado Mem[2]=16 no cenario 10");
                if (output_data !== 32'd2)  $fatal(1, "Esperado output_data=2 no cenario 10");
            end else if (scenario == 20) begin
                if (ram.mem[1] !== (32'd20 - 32'd16)) $fatal(1, "Esperado Mem[1]=4 no cenario 20");
                if (ram.mem[2] !== 32'd15)           $fatal(1, "Esperado Mem[2]=15 no cenario 20");
                if (output_data !== 32'd1)           $fatal(1, "Esperado output_data=1 no cenario 20");
            end

            if (R5 !== 32'd16) $fatal(1, "Reg5 deveria ser 16 (R1+R2)");
            if (R4 !== (scenario - 32'd16)) $fatal(1, "Reg4 deveria ser input_data-16");

            $display("=== OK (cenario %0d) ===\n", scenario);
        end
    endtask

    task run_scenario(input integer value);
        begin
            load_program();
            do_reset();
            input_data = value;
            wait_final();
            print_and_check(value);
        end
    endtask

    initial begin
        run_scenario(10);
        run_scenario(20);
        $display("Todas as verificacoes passaram. Encerrando simulacao.");
        $finish;
    end
endmodule

wave.vcd
$date
	Tue Aug 26 22:33:36 2025
$end
$version
	Icarus Verilog
$end
$timescale
	1ps
$end
$scope module tb_top $end
$var wire 32 ! output_data [31:0] $end
$var wire 1 " mem_op $end
$var wire 1 # mem_enable $end
$var wire 32 $ MBR_out [31:0] $end
$var wire 32 % MBR_in [31:0] $end
$var wire 32 & MAR [31:0] $end
$var reg 1 ' clock $end
$var reg 32 ( input_data [31:0] $end
$var reg 1 ) reset $end
$scope module dut $end
$var wire 1 ' clock $end
$var wire 32 * input_data [31:0] $end
$var wire 1 ) reset $end
$var wire 32 + rt_data [31:0] $end
$var wire 5 , rt [4:0] $end
$var wire 32 - rs_data [31:0] $end
$var wire 5 . rs [4:0] $end
$var wire 5 / rd [4:0] $end
$var wire 6 0 opcode [5:0] $end
$var wire 26 1 off26 [25:0] $end
$var wire 16 2 imm16 [15:0] $end
$var wire 6 3 funct [5:0] $end
$var wire 1 4 alu_z $end
$var wire 32 5 alu_y [31:0] $end
$var wire 1 6 alu_n $end
$var wire 32 7 OFF26_SEX [31:0] $end
$var wire 32 8 MBR_in [31:0] $end
$var wire 32 9 IMM_ZEXT [31:0] $end
$var wire 32 : IMM_SEXT [31:0] $end
$var parameter 3 ; ALU_ADD $end
$var parameter 3 < ALU_AND $end
$var parameter 3 = ALU_DIV $end
$var parameter 3 > ALU_MUL $end
$var parameter 3 ? ALU_NOT $end
$var parameter 3 @ ALU_OR $end
$var parameter 3 A ALU_SUB $end
$var parameter 6 B FUNCT_ADD $end
$var parameter 6 C FUNCT_AND $end
$var parameter 6 D FUNCT_DIV $end
$var parameter 6 E FUNCT_MUL $end
$var parameter 6 F FUNCT_NOT $end
$var parameter 6 G FUNCT_OR $end
$var parameter 6 H FUNCT_SUB $end
$var parameter 6 I OP_JE $end
$var parameter 6 J OP_JG $end
$var parameter 6 K OP_JGE $end
$var parameter 6 L OP_JL $end
$var parameter 6 M OP_JLE $end
$var parameter 6 N OP_JMP $end
$var parameter 6 O OP_JNE $end
$var parameter 6 P OP_LCH $end
$var parameter 6 Q OP_LCL $end
$var parameter 6 R OP_LOAD $end
$var parameter 6 S OP_LOADEXT $end
$var parameter 6 T OP_RTYPE $end
$var parameter 6 U OP_STORE $end
$var parameter 6 V OP_STOREEXT $end
$var parameter 4 W S_BRANCH $end
$var parameter 4 X S_DECODE $end
$var parameter 4 Y S_EXEC_R $end
$var parameter 4 Z S_FETCH $end
$var parameter 4 [ S_FETCH_WAIT $end
$var parameter 4 \ S_JUMP $end
$var parameter 4 ] S_LCH $end
$var parameter 4 ^ S_LCL $end
$var parameter 4 _ S_LOADEXT $end
$var parameter 4 ` S_MEM_ADDR $end
$var parameter 4 a S_MEM_READ $end
$var parameter 4 b S_MEM_READ_WAIT $end
$var parameter 4 c S_MEM_WRITE $end
$var parameter 4 d S_MEM_WRITE_WAIT $end
$var parameter 4 e S_RESET $end
$var parameter 4 f S_STOREEXT $end
$var reg 32 g IR [31:0] $end
$var reg 32 h MAR [31:0] $end
$var reg 32 i MBR_out [31:0] $end
$var reg 32 j PC [31:0] $end
$var reg 32 k alu_a [31:0] $end
$var reg 32 l alu_b [31:0] $end
$var reg 3 m alu_op [2:0] $end
$var reg 32 n eff_addr [31:0] $end
$var reg 1 o flagN $end
$var reg 1 p flagZ $end
$var reg 1 # mem_enable $end
$var reg 1 " mem_op $end
$var reg 4 q next_state [3:0] $end
$var reg 32 r output_data [31:0] $end
$var reg 32 s output_data_next [31:0] $end
$var reg 5 t rf_waddr [4:0] $end
$var reg 32 u rf_wdata [31:0] $end
$var reg 1 v rf_we $end
$var reg 4 w state [3:0] $end
$var reg 1 x take_branch $end
$scope module ULA $end
$var wire 32 y a [31:0] $end
$var wire 32 z b [31:0] $end
$var wire 3 { op [2:0] $end
$var wire 1 4 Z $end
$var wire 1 6 N $end
$var reg 32 | y [31:0] $end
$upscope $end
$scope module rf $end
$var wire 1 ' clock $end
$var wire 5 } rs [4:0] $end
$var wire 32 ~ rs_data [31:0] $end
$var wire 5 !" rt [4:0] $end
$var wire 32 "" rt_data [31:0] $end
$var wire 5 #" waddr [4:0] $end
$var wire 32 $" wdata [31:0] $end
$var wire 1 v we $end
$var integer 32 %" i [31:0] $end
$upscope $end
$upscope $end
$scope module ram $end
$var wire 32 &" MAR [31:0] $end
$var wire 32 '" MBR_out [31:0] $end
$var wire 1 ' clock $end
$var wire 1 # mem_enable $end
$var wire 1 " mem_op $end
$var parameter 32 (" MEM_WORDS $end
$var reg 32 )" MBR_in [31:0] $end
$upscope $end
$scope task do_reset $end
$upscope $end
$scope task load_program $end
$var integer 32 *" i [31:0] $end
$upscope $end
$scope task print_and_check $end
$var reg 32 +" R0 [31:0] $end
$var reg 32 ," R1 [31:0] $end
$var reg 32 -" R2 [31:0] $end
$var reg 32 ." R3 [31:0] $end
$var reg 32 /" R4 [31:0] $end
$var reg 32 0" R5 [31:0] $end
$var integer 32 1" scenario [31:0] $end
$upscope $end
$scope task run_scenario $end
$var integer 32 2" value [31:0] $end
$upscope $end
$scope task wait_final $end
$var integer 32 3" stuck [31:0] $end
$upscope $end
$upscope $end
$enddefinitions $end
$comment Show the parameter values. $end
$dumpall
b100000000 ("
b1111 f
b0 e
b1011 d
b1010 c
b1001 b
b1000 a
b111 `
b1110 _
b110 ^
b101 ]
b1101 \
b10 [
b1 Z
b100 Y
b11 X
b1100 W
b101010 V
b101011 U
b0 T
b100000 S
b100011 R
b1101 Q
b1111 P
b101 O
b10 N
b11111 M
b11110 L
b111 K
b110 J
b100 I
b100010 H
b100101 G
b101111 F
b11000 E
b11010 D
b100100 C
b100000 B
b1 A
b11 @
b100 ?
b101 >
b110 =
b10 <
b0 ;
$end
#0
$dumpvars
bx 3"
b1010 2"
bx 1"
bx 0"
bx /"
bx ."
bx -"
bx ,"
bx +"
b100000000 *"
bx )"
bx '"
bx &"
b100000 %"
bx $"
bx #"
bx ""
bx !"
bx ~
bx }
bx |
bx {
bx z
bx y
xx
bx w
xv
bx u
bx t
bx s
bx r
bx q
xp
xo
bx n
bx m
bx l
bx k
bx j
bx i
bx h
bx g
bx :
b0xxxxxxxxxxxxxxxx 9
bx 8
bx 7
x6
bx 5
x4
bx 3
bx 2
bx 1
bx 0
bx /
bx .
bx -
bx ,
bx +
bx *
1)
bx (
0'
bx &
bx %
bx $
x#
x"
bx !
$end
#5000
06
14
b0 5
b0 |
b0 l
b0 z
b0 k
b0 y
b0 0
b0 -
b0 ~
b0 .
b0 }
b0 +
b0 ""
b0 ,
b0 !"
b0 /
b0 3
b0 :
b0 9
b0 2
b0 7
b0 1
b0 m
b0 {
b0 u
b0 $"
b0 t
b0 #"
b1 q
b0 s
b0 !
b0 r
0v
b0 $
b0 i
b0 '"
b0 &
b0 h
b0 &"
0"
0#
0o
0p
b0 g
b0 j
b0 w
1'
#10000
0'
#15000
1'
#20000
0'
#25000
1#
b1 w
b10 q
b0 3"
b1010 (
b1010 *
0)
1'
#30000
0'
#35000
b11 q
0#
b1000000000000000000000000011 %
b1000000000000000000000000011 8
b1000000000000000000000000011 )"
b10 w
1'
#40000
0'
#45000
b1101 q
b10 0
b11 3
b11 :
b11 9
b11 2
b11 7
b11 1
b11 w
b1000000000000000000000000011 g
1'
#50000
0'
#55000
b1 q
b1101 w
1'
#60000
0'
#65000
b10 q
b11 &
b11 h
b11 &"
1#
b1 w
b11 j
1'
#70000
0'
#75000
b11 q
b0 &
b0 h
b0 &"
0#
b111100000000000000000000000000 %
b111100000000000000000000000000 8
b111100000000000000000000000000 )"
b10 w
1'
#80000
0'
#85000
b101 q
b1111 0
b0 3
b0 :
b0 9
b0 2
b0 7
b0 1
b11 w
b111100000000000000000000000000 g
1'
#90000
0'
#95000
b1 q
1v
b101 w
1'
#100000
0'
#105000
b10 q
b100 &
b100 h
b100 &"
1#
0v
b1 w
b100 j
1'
#110000
0'
#115000
b11 q
b0 &
b0 h
b0 &"
0#
b110100000000000000000000000001 %
b110100000000000000000000000001 8
b110100000000000000000000000001 )"
b10 w
1'
#120000
0'
#125000
b110 q
b1101 0
b1 3
b1 :
b1 9
b1 2
b1 7
b1 1
b11 w
b110100000000000000000000000001 g
1'
#130000
0'
#135000
b1 q
b1 u
b1 $"
1v
b110 w
1'
#140000
0'
#145000
04
b10 5
b10 |
b10 q
b101 &
b101 h
b101 &"
1#
b1 l
b1 z
b1 k
b1 y
b0 u
b0 $"
0v
b1 -
b1 ~
b1 +
b1 ""
b1 w
b101 j
1'
#150000
0'
#155000
b11 q
b0 &
b0 h
b0 &"
0#
b10001100000000010000000000000000 %
b10001100000000010000000000000000 8
b10001100000000010000000000000000 )"
b10 w
1'
#160000
0'
#165000
b1 5
b1 |
b111 q
b0 l
b0 z
b100011 0
b0 +
b0 ""
b1 ,
b1 !"
b0 3
b0 :
b0 9
b0 2
b10000000000000000 7
b10000000000000000 1
b11 w
b10001100000000010000000000000000 g
1'
#170000
0'
#175000
b1000 q
b111 w
1'
#180000
0'
#185000
b1001 q
b1 &
b1 h
b1 &"
1#
b1000 w
b1 n
1'
#190000
0'
#195000
b1 q
b1 u
b1 $"
b1 t
b1 #"
1v
b0 &
b0 h
b0 &"
0#
b1 %
b1 8
b1 )"
b1001 w
1'
#200000
0'
#205000
b10 5
b10 |
b10 q
b110 &
b110 h
b110 &"
1#
b1 l
b1 z
b0 u
b0 $"
b0 t
b0 #"
0v
b1 +
b1 ""
b1 w
b110 j
1'
#210000
0'
#215000
b11 q
b0 &
b0 h
b0 &"
0#
b110100000000000000000000000010 %
b110100000000000000000000000010 8
b110100000000000000000000000010 )"
b10 w
1'
#220000
0'
#225000
b110 q
b1101 0
b0 ,
b0 !"
b10 3
b10 :
b10 9
b10 2
b10 7
b10 1
b11 w
b110100000000000000000000000010 g
1'
#230000
0'
#235000
b1 q
b10 u
b10 $"
1v
b110 w
1'
#240000
0'
#245000
b100 5
b100 |
b10 q
b111 &
b111 h
b111 &"
1#
b10 l
b10 z
b10 k
b10 y
b0 u
b0 $"
0v
b10 -
b10 ~
b10 +
b10 ""
b1 w
b111 j
1'
#250000
0'
#255000
b11 q
b0 &
b0 h
b0 &"
0#
b10001100000000100000000000000000 %
b10001100000000100000000000000000 8
b10001100000000100000000000000000 )"
b10 w
1'
#260000
0'
#265000
b10 5
b10 |
b111 q
b0 l
b0 z
b100011 0
b0 +
b0 ""
b10 ,
b10 !"
b0 3
b0 :
b0 9
b0 2
b100000000000000000 7
b100000000000000000 1
b11 w
b10001100000000100000000000000000 g
1'
#270000
0'
#275000
b1000 q
b111 w
1'
#280000
0'
#285000
b1001 q
b10 &
b10 h
b10 &"
1#
b1000 w
b10 n
1'
#290000
0'
#295000
b1 q
b1111 u
b1111 $"
b10 t
b10 #"
1v
b0 &
b0 h
b0 &"
0#
b1111 %
b1111 8
b1111 )"
b1001 w
1'
#300000
0'
#305000
b10001 5
b10001 |
b10 q
b1000 &
b1000 h
b1000 &"
1#
b1111 l
b1111 z
b0 u
b0 $"
b0 t
b0 #"
0v
b1111 +
b1111 ""
b1 w
b1000 j
1'
#310000
0'
#315000
b11 q
b0 &
b0 h
b0 &"
0#
b10000000000000110000000000000000 %
b10000000000000110000000000000000 8
b10000000000000110000000000000000 )"
b10 w
1'
#320000
0'
#325000
b10 5
b10 |
b1110 q
b0 l
b0 z
b100000 0
b0 +
b0 ""
b11 ,
b11 !"
b110000000000000000 7
b110000000000000000 1
b11 w
b10000000000000110000000000000000 g
1'
#330000
0'
#335000
b1 q
b1010 u
b1010 $"
b11 t
b11 #"
1v
b1110 w
1'
#340000
0'
#345000
b1100 5
b1100 |
b10 q
b1001 &
b1001 h
b1001 &"
1#
b1010 l
b1010 z
b0 u
b0 $"
b0 t
b0 #"
0v
b1010 +
b1010 ""
b1 w
b1001 j
1'
#350000
0'
#355000
b11 q
b0 &
b0 h
b0 &"
0#
b1000100010100000100000 %
b1000100010100000100000 8
b1000100010100000100000 )"
b10 w
1'
#360000
0'
#365000
b10000 5
b10000 |
b100 q
b1111 l
b1111 z
b1 k
b1 y
b0 0
b1 -
b1 ~
b1 .
b1 }
b1111 +
b1111 ""
b10 ,
b10 !"
b101 /
b100000 3
b10100000100000 :
b10100000100000 9
b10100000100000 2
b1000100010100000100000 7
b1000100010100000100000 1
b11 w
b1000100010100000100000 g
1'
#370000
0'
#375000
b1 q
b10000 u
b10000 $"
b101 t
b101 #"
1v
b100 w
1'
#380000
0'
#385000
b10 q
b1010 &
b1010 h
b1010 &"
1#
b0 u
b0 $"
b0 t
b0 #"
0v
b1 w
b1010 j
1'
#390000
0'
#395000
b11 q
b0 &
b0 h
b0 &"
0#
b11001010010000000100010 %
b11001010010000000100010 8
b11001010010000000100010 )"
b10 w
1'
#400000
0'
#405000
b11010 5
b11010 |
b100 q
b10000 l
b10000 z
b1010 k
b1010 y
b1010 -
b1010 ~
b11 .
b11 }
b10000 +
b10000 ""
b101 ,
b101 !"
b100 /
b100010 3
b10000000100010 :
b10000000100010 9
b10000000100010 2
b11001010010000000100010 7
b11001010010000000100010 1
b11 w
b11001010010000000100010 g
1'
#410000
0'
#415000
16
b11111111111111111111111111111010 5
b11111111111111111111111111111010 |
b1 q
b11111111111111111111111111111010 u
b11111111111111111111111111111010 $"
b100 t
b100 #"
1v
b1 m
b1 {
b100 w
1'
#420000
0'
#425000
06
b11010 5
b11010 |
b10 q
b1011 &
b1011 h
b1011 &"
1#
b0 m
b0 {
b0 u
b0 $"
b0 t
b0 #"
0v
b1 w
b1011 j
1o
1'
#430000
0'
#435000
b11 q
b0 &
b0 h
b0 &"
0#
b11100000000000000000000000100 %
b11100000000000000000000000100 8
b11100000000000000000000000100 )"
b10 w
1'
#440000
0'
#445000
b100 5
b100 |
b1100 q
b10 l
b10 z
b10 k
b10 y
b111 0
b10 -
b10 ~
b0 .
b0 }
b10 +
b10 ""
b0 ,
b0 !"
b0 /
b100 3
b100 :
b100 9
b100 2
b100 7
b100 1
b11 w
b11100000000000000000000000100 g
1'
#450000
0'
#455000
b1 q
b1100 w
1'
#460000
0'
#465000
b10 q
b1100 &
b1100 h
b1100 &"
1#
b1 w
b1100 j
0x
1'
#470000
0'
#475000
b11 q
b0 &
b0 h
b0 &"
0#
b10101100000001010000000000000000 %
b10101100000001010000000000000000 8
b10101100000001010000000000000000 )"
b10 w
1'
#480000
0'
#485000
b10010 5
b10010 |
b111 q
b10000 l
b10000 z
b101011 0
b10000 +
b10000 ""
b101 ,
b101 !"
b0 3
b0 :
b0 9
b0 2
b1010000000000000000 7
b1010000000000000000 1
b11 w
b10101100000001010000000000000000 g
1'
#490000
0'
#495000
b10 5
b10 |
b1010 q
b0 l
b0 z
b111 w
1'
#500000
0'
#505000
b10010 5
b10010 |
b1011 q
b10000 $
b10000 i
b10000 '"
b10 &
b10 h
b10 &"
1"
1#
b10000 l
b10000 z
b1010 w
1'
#510000
0'
#515000
b1 q
b0 $
b0 i
b0 '"
b0 &
b0 h
b0 &"
0"
0#
b1011 w
1'
#520000
0'
#525000
b10 q
b1101 &
b1101 h
b1101 &"
1#
b1 w
b1101 j
1'
#530000
0'
#535000
b11 q
b0 &
b0 h
b0 &"
0#
b10101000000000000000000000000000 %
b10101000000000000000000000000000 8
b10101000000000000000000000000000 )"
b10 w
1'
#540000
0'
#545000
b100 5
b100 |
b1111 q
b10 l
b10 z
b101010 0
b10 +
b10 ""
b0 ,
b0 !"
b0 7
b0 1
b11 w
b10101000000000000000000000000000 g
1'
#550000
0'
#555000
b1 q
b10 s
b1111 w
1'
#560000
0'
#565000
b10 q
b1110 &
b1110 h
b1110 &"
1#
b10 !
b10 r
b1 w
b1110 j
1'
#570000
0'
#575000
b11 q
b0 &
b0 h
b0 &"
0#
b1000000000000000000000000100 %
b1000000000000000000000000100 8
b1000000000000000000000000100 )"
b10 w
1'
#580000
0'
